tai_ttex-0.2.1.53.dist-info/licenses/LICENSE
tests/__init__.py
tests/config/__init__.py
tests/config/test_config.py
tests/config/test_configurable_object.py
tests/log/__init__.py
tests/log/coco/__init__.py
tests/log/coco/test_coco_events.py
tests/log/coco/test_coco_logging_integration.py
tests/log/coco/test_coco_splitter.py
tests/log/coco/test_coco_state.py
tests/log/coco/test_run_cocopp.py
tests/log/coco/postp/__init__.py
tests/log/coco/postp/test_info.py
tests/log/coco/postp/test_testbed.py
tests/log/coco/records/__init__.py
tests/log/coco/records/test_coco_info.py
tests/log/coco/records/test_coco_log.py
tests/log/coco/records/test_coco_log_dat.py
tests/log/coco/records/test_coco_log_tdat.py
tests/log/filter/__init__.py
tests/log/filter/test_event_keysplit_filter.py
tests/log/filter/test_key_filter.py
tests/log/formatter/__init__.py
tests/log/formatter/test_json_formatter.py
tests/log/formatter/test_key_formatter.py
tests/log/handler/__init__.py
tests/log/handler/test_manual_rotating_file_handler.py
tests/log/handler/test_wandb_handler.py
tests/log/utils/__init__.py
tests/log/utils/test_coco_logging_setup.py
tests/log/utils/test_logging_setup.py
tests/log/utils/test_snapshot.py
tests/log/utils/test_wandb_logging_setup.py
tests/utils/__init__.py
tests/utils/dummy_log_handler.py
ttex/__init__.py
ttex/config/__init__.py
ttex/config/config.py
ttex/config/configurable_object.py
ttex/log/__init__.py
ttex/log/coco/__init__.py
ttex/log/coco/coco_events.py
ttex/log/coco/coco_splitter.py
ttex/log/coco/coco_state.py
ttex/log/coco/logging_config.py
ttex/log/coco/run_cocopp.py
ttex/log/coco/postp/__init__.py
ttex/log/coco/postp/info.py
ttex/log/coco/postp/testbed.py
ttex/log/coco/record/__init__.py
ttex/log/coco/record/info.py
ttex/log/coco/record/log.py
ttex/log/coco/record/log_dat.py
ttex/log/coco/record/log_tdat.py
ttex/log/filter/__init__.py
ttex/log/filter/event_keysplit_filter.py
ttex/log/filter/key_filter.py
ttex/log/formatter/__init__.py
ttex/log/formatter/json_formatter.py
ttex/log/formatter/key_formatter.py
tai_ttex-0.2.1.53.dist-info/METADATA
tai_ttex-0.2.1.53.dist-info/WHEEL
tai_ttex-0.2.1.53.dist-info/top_level.txt
tai_ttex-0.2.1.53.dist-info/RECORD
