Metadata-Version: 2.4
Name: tai_ttex
Version: 0.2.1.53
License: GPL3
License-File: LICENSE
Requires-Dist: wandb
Requires-Dist: numpy
Requires-Dist: cocopp
Dynamic: description
Dynamic: description-content-type
Dynamic: license
Dynamic: license-file
Dynamic: requires-dist
